MANIFEST.in
README.md
cModPyAlignment.cpython-37m-x86_64-linux-gnu.so
setup.cfg
setup.py
/data/Codes/vspscripts/vspscripts/alignment/cModPyAlignment.cpp
/data/Codes/vspscripts/vspscripts/alignment/Clibrary/src/ICPair.cpp
/data/Codes/vspscripts/vspscripts/alignment/Clibrary/src/Match.cpp
/data/Codes/vspscripts/vspscripts/alignment/Clibrary/src/SimMat.cpp
/data/Codes/vspscripts/vspscripts/alignment/Clibrary/src/utils.cpp
vspscripts/__init__.py
vspscripts.egg-info/PKG-INFO
vspscripts.egg-info/SOURCES.txt
vspscripts.egg-info/dependency_links.txt
vspscripts.egg-info/entry_points.txt
vspscripts.egg-info/requires.txt
vspscripts.egg-info/top_level.txt
vspscripts/alignment/PyAlignment.py
vspscripts/alignment/PyMatch.py
vspscripts/alignment/__init__.py
vspscripts/alignment/alignment_all.py
vspscripts/alignment/cModPyAlignment.cpython-37m-x86_64-linux-gnu.so
vspscripts/alignment/setup.py
vspscripts/alignment/test.py
vspscripts/alignment/matching/__init__.py
vspscripts/alignment/matching/dist.py
vspscripts/alignment/matching/matching.py
vspscripts/alignment/tools/__init__.py
vspscripts/alignment/tools/evaluation.py
vspscripts/alignment/tools/show_imgs.py
vspscripts/alignment/tools/show_matchTemp.py
vspscripts/alignment/tools/show_pixel.py
vspscripts/alignment/utils/__init__.py
vspscripts/alignment/utils/ann.py
vspscripts/alignment/utils/gol.py
vspscripts/alignment/utils/img.py
vspscripts/alignment/utils/mat.py
vspscripts/alignment/utils/utils.py
vspscripts/annotation/__init__.py
vspscripts/annotation/cityscapesLabelTool.py
vspscripts/annotation/icons/back.png
vspscripts/annotation/icons/checked6.png
vspscripts/annotation/icons/checked6_red.png
vspscripts/annotation/icons/clearpolygon.png
vspscripts/annotation/icons/deleteobject.png
vspscripts/annotation/icons/exit.png
vspscripts/annotation/icons/filepath.png
vspscripts/annotation/icons/help19.png
vspscripts/annotation/icons/highlight.png
vspscripts/annotation/icons/layerdown.png
vspscripts/annotation/icons/layerup.png
vspscripts/annotation/icons/minus.png
vspscripts/annotation/icons/modify.png
vspscripts/annotation/icons/newobject.png
vspscripts/annotation/icons/next.png
vspscripts/annotation/icons/open.png
