Metadata-Version: 2.1
Name: vspscripts
Version: 1.2.0
Summary: Scripts for the VSP Dataset
Home-page: UNKNOWN
Author: WJG
Author-email: wangjiangong2018@ia.ac.cn
License: MIT license
Platform: UNKNOWN
Provides-Extra: gui
